{
  "events": [
    {
      "id": 1,
      "event": "call",
      "thread_id": 4520,
      "defined_class": "ActionDispatch::Integration::Runner",
      "method_id": "before_setup",
      "path": "/usr/local/bundle/gems/actionpack-7.0.4/lib/action_dispatch/testing/integration.rb",
      "lineno": 329,
      "static": false,
      "receiver": {
        "class": "StaticPagesControllerTest",
        "object_id": 91140,
        "value": "#<StaticPagesControllerTest:0x0000ffffacccf400>"
      }
    },
    {
      "id": 2,
      "event": "call",
      "thread_id": 4520,
      "defined_class": "ActiveSupport::Callbacks::CallbackSequence",
      "method_id": "invoke_before",
      "path": "/usr/local/bundle/gems/activesupport-7.0.4/lib/active_support/callbacks.rb",
      "lineno": 594,
      "static": false,
      "parameters": [
        {
          "name": "arg",
          "class": "ActiveSupport::Callbacks::Filters::Environment",
          "object_id": 91180,
          "value": null,
          "kind": "req"
        }
      ],
      "receiver": {
        "class": "ActiveSupport::Callbacks::CallbackSequence",
        "object_id": 28280,
        "value": "#<ActiveSupport::Callbacks::CallbackSequence:0x0000ffffab8295f0>"
      }
    },
    {
      "id": 3,
      "event": "return",
      "thread_id": 4520,
      "parent_id": 2,
      "elapsed": 7.080000159476185e-7,
      "elapsed_instrumentation": 0.00004320800007917569,
      "return_value": {
        "class": "Array",
        "value": "[]",
        "object_id": 28300,
        "size": 0
      }
    },
    {
      "id": 4,
      "event": "call",
      "thread_id": 4520,
      "defined_class": "ActiveSupport::Callbacks::CallbackSequence",
      "method_id": "invoke_after",
      "path": "/usr/local/bundle/gems/activesupport-7.0.4/lib/active_support/callbacks.rb",
      "lineno": 598,
      "static": false,
      "parameters": [
        {
          "name": "arg",
          "class": "ActiveSupport::Callbacks::Filters::Environment",
          "object_id": 91180,
          "value": null,
          "kind": "req"
        }
      ],
      "receiver": {
        "class": "ActiveSupport::Callbacks::CallbackSequence",
        "object_id": 28280,
        "value": "#<ActiveSupport::Callbacks::CallbackSequence:0x0000ffffab8295f0>"
      }
    },
    {
      "id": 5,
      "event": "return",
      "thread_id": 4520,
      "parent_id": 4,
      "elapsed": 0.000006500000154119334,
      "elapsed_instrumentation": 0.000028749999955834937,
      "return_value": {
        "class": "Array",
        "value": "[#<Proc:0x0000ffffab828a38 /usr/local/bundle/gems/activesupport-7.0.4/lib/active_support/callbacks.rb]",
        "object_id": 28320,
        "size": 1
      }
    },
    {
      "id": 6,
      "event": "call",
      "thread_id": 4520,
      "defined_class": "Logger::LogDevice",
      "method_id": "write",
      "path": "/usr/local/lib/ruby/3.1.0/logger/log_device.rb",
      "lineno": 31,
      "static": false,
      "parameters": [
        {
          "name": "message",
          "class": "String",
          "object_id": 91200,
          "value": "  \u001b[1m\u001b[36mTRANSACTION (0.1ms)\u001b[0m  \u001b[1m\u001b[36mbegin transaction\u001b[0m\n",
          "kind": "req"
        }
      ],
      "receiver": {
        "class": "Logger::LogDevice",
        "object_id": 9040,
        "value": "#<Logger::LogDevice:0x0000ffffab8fa588>"
      }
    },
    {
      "id": 7,
      "event": "return",
      "thread_id": 4520,
      "parent_id": 6,
      "elapsed": 0.0005797500000426226,
      "elapsed_instrumentation": 0.00006808300008742663,
      "return_value": {
        "class": "Integer",
        "value": "67",
        "object_id": 135
      }
    },
    {
      "id": 8,
      "event": "call",
      "thread_id": 4520,
      "sql_query": {
        "sql": "begin transaction",
        "database_type": "sqlite"
      }
    },
    {
      "id": 9,
      "event": "return",
      "thread_id": 4520,
      "parent_id": 8,
      "elapsed": 0.000783083,
      "elapsed_instrumentation": 0.00006287499991231016
    },
    {
      "id": 10,
      "event": "call",
      "thread_id": 4520,
      "defined_class": "Logger::LogDevice",
      "method_id": "write",
      "path": "/usr/local/lib/ruby/3.1.0/logger/log_device.rb",
      "lineno": 31,
      "static": false,
      "parameters": [
        {
          "name": "message",
          "class": "String",
          "object_id": 91220,
          "value": "--------------------------------------------------\n",
          "kind": "req"
        }
      ],
      "receiver": {
        "class": "Logger::LogDevice",
        "object_id": 9040,
        "value": "#<Logger::LogDevice:0x0000ffffab8fa588>"
      }
    },
    {
      "id": 11,
      "event": "return",
      "thread_id": 4520,
      "parent_id": 10,
      "elapsed": 0.0004098750000594009,
      "elapsed_instrumentation": 0.00007183399998211826,
      "return_value": {
        "class": "Integer",
        "value": "51",
        "object_id": 103
      }
    },
    {
      "id": 12,
      "event": "call",
      "thread_id": 4520,
      "defined_class": "Logger::LogDevice",
      "method_id": "write",
      "path": "/usr/local/lib/ruby/3.1.0/logger/log_device.rb",
      "lineno": 31,
      "static": false,
      "parameters": [
        {
          "name": "message",
          "class": "String",
          "object_id": 91240,
          "value": "StaticPagesControllerTest: test_should_get_contact\n",
          "kind": "req"
        }
      ],
      "receiver": {
        "class": "Logger::LogDevice",
        "object_id": 9040,
        "value": "#<Logger::LogDevice:0x0000ffffab8fa588>"
      }
    },
    {
      "id": 13,
      "event": "return",
      "thread_id": 4520,
      "parent_id": 12,
      "elapsed": 0.00044604100003198255,
      "elapsed_instrumentation": 0.00005887499992240919,
      "return_value": {
        "class": "Integer",
        "value": "51",
        "object_id": 103
      }
    },
    {
      "id": 14,
      "event": "call",
      "thread_id": 4520,
      "defined_class": "Logger::LogDevice",
      "method_id": "write",
      "path": "/usr/local/lib/ruby/3.1.0/logger/log_device.rb",
      "lineno": 31,
      "static": false,
      "parameters": [
        {
          "name": "message",
          "class": "String",
          "object_id": 91260,
          "value": "--------------------------------------------------\n",
          "kind": "req"
        }
      ],
      "receiver": {
        "class": "Logger::LogDevice",
        "object_id": 9040,
        "value": "#<Logger::LogDevice:0x0000ffffab8fa588>"
      }
    },
    {
      "id": 15,
      "event": "return",
      "thread_id": 4520,
      "parent_id": 14,
      "elapsed": 0.0005065830000603455,
      "elapsed_instrumentation": 0.00006499999972220394,
      "return_value": {
        "class": "Integer",
        "value": "51",
        "object_id": 103
      }
    },
    {
      "id": 16,
      "event": "call",
      "thread_id": 4520,
      "defined_class": "ActiveSupport::Callbacks::CallbackSequence",
      "method_id": "invoke_before",
      "path": "/usr/local/bundle/gems/activesupport-7.0.4/lib/active_support/callbacks.rb",
      "lineno": 594,
      "static": false,
      "parameters": [
        {
          "name": "arg",
          "class": "ActiveSupport::Callbacks::Filters::Environment",
          "object_id": 91280,
          "value": null,
          "kind": "req"
        }
      ],
      "receiver": {
        "class": "ActiveSupport::Callbacks::CallbackSequence",
        "object_id": 40380,
        "value": "#<ActiveSupport::Callbacks::CallbackSequence:0x0000ffffa9d8d638>"
      }
    },
    {
      "id": 17,
      "event": "return",
      "thread_id": 4520,
      "parent_id": 16,
      "elapsed": 0.00004770900000039546,
      "elapsed_instrumentation": 0.00005412500013335375,
      "return_value": {
        "class": "Array",
        "value": "[#<Proc:0x0000ffffa9d8d228 /usr/local/bundle/gems/activesupport-7.0.4/lib/active_support/callbacks.rb, #<Proc:0x0000ffffa9d8d368 /usr/local/bundle/gems/activesupport-7.0.4/lib/active_support/callbacks.rb]",
        "object_id": 40480,
        "size": 2
      }
    },
    {
      "id": 18,
      "event": "call",
      "thread_id": 4520,
      "defined_class": "ActiveSupport::Callbacks::CallbackSequence",
      "method_id": "invoke_after",
      "path": "/usr/local/bundle/gems/activesupport-7.0.4/lib/active_support/callbacks.rb",
      "lineno": 598,
      "static": false,
      "parameters": [
        {
          "name": "arg",
          "class": "ActiveSupport::Callbacks::Filters::Environment",
          "object_id": 91280,
          "value": null,
          "kind": "req"
        }
      ],
      "receiver": {
        "class": "ActiveSupport::Callbacks::CallbackSequence",
        "object_id": 40380,
        "value": "#<ActiveSupport::Callbacks::CallbackSequence:0x0000ffffa9d8d638>"
      }
    },
    {
      "id": 19,
      "event": "return",
      "thread_id": 4520,
      "parent_id": 18,
      "elapsed": 6.660000053670956e-7,
      "elapsed_instrumentation": 0.000023084000076778466,
      "return_value": {
        "class": "Array",
        "value": "[]",
        "object_id": 40500,
        "size": 0
      }
    },
    {
      "id": 20,
      "event": "return",
      "thread_id": 4520,
      "parent_id": 1,
      "elapsed": 0.003064834000042538,
      "elapsed_instrumentation": 0.00009762400009094563,
      "return_value": {
        "class": "TrueClass",
        "value": "true",
        "object_id": 20
      }
    },
    {
      "id": 21,
      "event": "call",
      "thread_id": 4520,
      "http_server_request": {
        "request_method": "GET",
        "path_info": "/contact",
        "normalized_path_info": "/contact",
        "headers": {
          "Version": "HTTP/1.0",
          "Host": "www.example.com",
          "Accept": "text/xml,application/xml,application/xhtml+xml,text/html;q=0.9,text/plain;q=0.8,image/png,*/*;q=0.5",
          "Content-Length": "0"
        }
      }
    },
    {
      "id": 22,
      "event": "call",
      "thread_id": 4520,
      "defined_class": "ActiveSupport::Callbacks::CallbackSequence",
      "method_id": "invoke_before",
      "path": "/usr/local/bundle/gems/activesupport-7.0.4/lib/active_support/callbacks.rb",
      "lineno": 594,
      "static": false,
      "parameters": [
        {
          "name": "arg",
          "class": "ActiveSupport::Callbacks::Filters::Environment",
          "object_id": 91300,
          "value": null,
          "kind": "req"
        }
      ],
      "receiver": {
        "class": "ActiveSupport::Callbacks::CallbackSequence",
        "object_id": 50280,
        "value": "#<ActiveSupport::Callbacks::CallbackSequence:0x0000ffffaa5cf7b0>"
      }
    },
    {
      "id": 23,
      "event": "return",
      "thread_id": 4520,
      "parent_id": 22,
      "elapsed": 0.00006654200001321442,
      "elapsed_instrumentation": 0.00028029099985360517,
      "return_value": {
        "class": "Array",
        "value": "[#<Proc:0x0000ffffaa5cebd0 /usr/local/bundle/gems/activesupport-7.0.4/lib/active_support/callbacks.rb, #<Proc:0x0000ffffaa5ced88 /usr/local/bundle/gems/activesupport-7.0.4/lib/active_support/callbacks.rb, #<Proc:0x0000ffffaa5ceec8 /usr/local/bundle/gems/activesupport-7.0.4/lib/active_support/callbacks.rb, #<Proc:0x0000ffffaa5cf0d0 /usr/local/bundle/gems/activesupport-7.0.4/lib/active_support/callbacks.rb, #<Proc:0x0000ffffaa5cf288 /usr/local/bundle/gems/activesupport-7.0.4/lib/active_support/callbacks.rb]",
        "object_id": 50300,
        "size": 5
      }
    },
    {
      "id": 24,
      "event": "call",
      "thread_id": 4520,
      "defined_class": "ActiveSupport::Callbacks::CallbackSequence",
      "method_id": "invoke_after",
      "path": "/usr/local/bundle/gems/activesupport-7.0.4/lib/active_support/callbacks.rb",
      "lineno": 598,
      "static": false,
      "parameters": [
        {
          "name": "arg",
          "class": "ActiveSupport::Callbacks::Filters::Environment",
          "object_id": 91300,
          "value": null,
          "kind": "req"
        }
      ],
      "receiver": {
        "class": "ActiveSupport::Callbacks::CallbackSequence",
        "object_id": 50280,
        "value": "#<ActiveSupport::Callbacks::CallbackSequence:0x0000ffffaa5cf7b0>"
      }
    },
    {
      "id": 25,
      "event": "return",
      "thread_id": 4520,
      "parent_id": 24,
      "elapsed": 9.170000794256339e-7,
      "elapsed_instrumentation": 0.000024207999786085566,
      "return_value": {
        "class": "Array",
        "value": "[]",
        "object_id": 50320,
        "size": 0
      }
    },
    {
      "id": 26,
      "event": "call",
      "thread_id": 4520,
      "defined_class": "String",
      "method_id": "unpack",
      "path": "<internal:pack>",
      "lineno": 275,
      "static": false,
      "parameters": [
        {
          "name": "fmt",
          "class": "String",
          "object_id": 50340,
          "value": "NnnnnN",
          "kind": "req"
        },
        {
          "name": "offset",
          "class": "NilClass",
          "object_id": 8,
          "value": null,
          "kind": "key"
        }
      ],
      "receiver": {
        "class": "String",
        "object_id": 91320,
        "value": "7e\u0014_o__]\u0003_H\f_K_\u0010"
      }
    },
    {
      "id": 27,
      "event": "return",
      "thread_id": 4520,
      "parent_id": 26,
      "elapsed": 0.0000020420000055310084,
      "elapsed_instrumentation": 0.000049874999831445166,
      "return_value": {
        "class": "Array",
        "value": "[929371318, 28629, 45405, 965, 18444, 4031498768]",
        "object_id": 91340,
        "size": 6
      }
    },
    {
      "id": 28,
      "event": "call",
      "thread_id": 4520,
      "defined_class": "Logger::LogDevice",
      "method_id": "write",
      "path": "/usr/local/lib/ruby/3.1.0/logger/log_device.rb",
      "lineno": 31,
      "static": false,
      "parameters": [
        {
          "name": "message",
          "class": "String",
          "object_id": 91360,
          "value": "Started GET \"/contact\" for 127.0.0.1 at 2024-03-27 18:34:18 +0000\n",
          "kind": "req"
        }
      ],
      "receiver": {
        "class": "Logger::LogDevice",
        "object_id": 9040,
        "value": "#<Logger::LogDevice:0x0000ffffab8fa588>"
      }
    },
    {
      "id": 29,
      "event": "return",
      "thread_id": 4520,
      "parent_id": 28,
      "elapsed": 0.0006624170000577578,
      "elapsed_instrumentation": 0.000044207999962964095,
      "return_value": {
        "class": "Integer",
        "value": "66",
        "object_id": 133
      }
    },
    {
      "id": 30,
      "event": "call",
      "thread_id": 4520,
      "defined_class": "Logger::LogDevice",
      "method_id": "write",
      "path": "/usr/local/lib/ruby/3.1.0/logger/log_device.rb",
      "lineno": 31,
      "static": false,
      "parameters": [
        {
          "name": "message",
          "class": "String",
          "object_id": 91440,
          "value": "Processing by StaticPagesController#contact as HTML\n",
          "kind": "req"
        }
      ],
      "receiver": {
        "class": "Logger::LogDevice",
        "object_id": 9040,
        "value": "#<Logger::LogDevice:0x0000ffffab8fa588>"
      }
    },
    {
      "id": 31,
      "event": "return",
      "thread_id": 4520,
      "parent_id": 30,
      "elapsed": 0.0005396669998845027,
      "elapsed_instrumentation": 0.00031404199989992776,
      "return_value": {
        "class": "Integer",
        "value": "52",
        "object_id": 105
      }
    },
    {
      "id": 32,
      "event": "call",
      "thread_id": 4520,
      "defined_class": "ActiveSupport::Callbacks::CallbackSequence",
      "method_id": "invoke_before",
      "path": "/usr/local/bundle/gems/activesupport-7.0.4/lib/active_support/callbacks.rb",
      "lineno": 594,
      "static": false,
      "parameters": [
        {
          "name": "arg",
          "class": "ActiveSupport::Callbacks::Filters::Environment",
          "object_id": 91460,
          "value": null,
          "kind": "req"
        }
      ],
      "receiver": {
        "class": "ActiveSupport::Callbacks::CallbackSequence",
        "object_id": 91480,
        "value": "#<ActiveSupport::Callbacks::CallbackSequence:0x0000ffffab7fe058>"
      }
    },
    {
      "id": 33,
      "event": "return",
      "thread_id": 4520,
      "parent_id": 32,
      "elapsed": 0.00006662500004495087,
      "elapsed_instrumentation": 0.000060333000192258623,
      "return_value": {
        "class": "Array",
        "value": "[#<Proc:0x0000ffffab7fd5b8 /usr/local/bundle/gems/activesupport-7.0.4/lib/active_support/callbacks.rb]",
        "object_id": 91500,
        "size": 1
      }
    },
    {
      "id": 34,
      "event": "call",
      "thread_id": 4520,
      "defined_class": "ActiveSupport::Callbacks::CallbackSequence",
      "method_id": "invoke_before",
      "path": "/usr/local/bundle/gems/activesupport-7.0.4/lib/active_support/callbacks.rb",
      "lineno": 594,
      "static": false,
      "parameters": [
        {
          "name": "arg",
          "class": "ActiveSupport::Callbacks::Filters::Environment",
          "object_id": 91460,
          "value": null,
          "kind": "req"
        }
      ],
      "receiver": {
        "class": "ActiveSupport::Callbacks::CallbackSequence",
        "object_id": 91520,
        "value": "#<ActiveSupport::Callbacks::CallbackSequence:0x0000ffffab7fe8c8>"
      }
    },
    {
      "id": 35,
      "event": "return",
      "thread_id": 4520,
      "parent_id": 34,
      "elapsed": 0.004970124999999825,
      "elapsed_instrumentation": 0.00008562400012124272,
      "return_value": {
        "class": "Array",
        "value": "[#<Proc:0x0000ffffab7fe1e8 /usr/local/bundle/gems/activesupport-7.0.4/lib/active_support/callbacks.rb]",
        "object_id": 91540,
        "size": 1
      }
    },
    {
      "id": 36,
      "event": "call",
      "thread_id": 4520,
      "defined_class": "StaticPagesController",
      "method_id": "contact",
      "path": "app/controllers/static_pages_controller.rb",
      "lineno": 16,
      "static": false,
      "receiver": {
        "class": "StaticPagesController",
        "object_id": 91560,
        "value": "#<StaticPagesController:0x0000ffffacc99d50>"
      }
    },
    {
      "id": 37,
      "event": "return",
      "thread_id": 4520,
      "parent_id": 36,
      "elapsed": 0.000001624999867999577,
      "elapsed_instrumentation": 0.0000724580002042785
    },
    {
      "id": 38,
      "event": "call",
      "thread_id": 4520,
      "defined_class": "ActionView::Resolver",
      "method_id": "find_all",
      "path": "/usr/local/bundle/gems/actionview-7.0.4/lib/action_view/template/resolver.rb",
      "lineno": 62,
      "static": false,
      "parameters": [
        {
          "name": "name",
          "class": "String",
          "object_id": 91580,
          "value": "contact",
          "kind": "req"
        },
        {
          "name": "prefix",
          "class": "String",
          "object_id": 91600,
          "value": "static_pages",
          "kind": "opt"
        },
        {
          "name": "partial",
          "class": "FalseClass",
          "object_id": 0,
          "value": "false",
          "kind": "opt"
        },
        {
          "name": "details",
          "class": "Hash",
          "object_id": 91620,
          "value": "{:locale=>[:en], :formats=>[:html], :variants=>[], :handlers=>[:raw, :erb, :html, :builder, :ruby, :jbuilder]}",
          "kind": "opt",
          "size": 4
        },
        {
          "name": "key",
          "class": "ActionView::TemplateDetails::Requested",
          "object_id": 51860,
          "value": "#<ActionView::TemplateDetails::Requested:0x0000ffffa8abc798>",
          "kind": "opt"
        },
        {
          "name": "locals",
          "class": "Array",
          "object_id": 91640,
          "value": "[]",
          "kind": "opt",
          "size": 0
        }
      ],
      "receiver": {
        "class": "ActionView::FileSystemResolver",
        "object_id": 53980,
        "value": "/app/app/views"
      }
    },
    {
      "id": 39,
      "event": "return",
      "thread_id": 4520,
      "parent_id": 38,
      "elapsed": 0.001591417000099682,
      "elapsed_instrumentation": 0.000282833999790455,
      "return_value": {
        "class": "Array",
        "value": "[#<ActionView::Template:0x0000ffffab846ee8>]",
        "object_id": 91660,
        "size": 1
      }
    },
    {
      "id": 40,
      "event": "call",
      "thread_id": 4520,
      "defined_class": "ActionController::Renderers",
      "method_id": "render_to_body",
      "path": "/usr/local/bundle/gems/actionpack-7.0.4/lib/action_controller/metal/renderers.rb",
      "lineno": 140,
      "static": false,
      "parameters": [
        {
          "name": "options",
          "class": "Hash",
          "object_id": 91680,
          "value": "{:prefixes=>[static_pages, application], :template=>contact, :layout=>#<Proc:0x0000ffffab849738 /usr/local/bundle/gems/actionview-7.0.4/lib/action_view/layouts.rb:393>}",
          "kind": "req",
          "size": 3
        }
      ],
      "receiver": {
        "class": "StaticPagesController",
        "object_id": 91560,
        "value": "#<StaticPagesController:0x0000ffffacc99d50>"
      }
    },
    {
      "id": 41,
      "event": "call",
      "thread_id": 4520,
      "defined_class": "app_views_static_pages_contact_html_erb",
      "method_id": "render",
      "path": "app/views/static_pages/contact.html.erb",
      "static": true,
      "receiver": {
        "class": "ActionView::TemplateRenderer",
        "object_id": 92700,
        "value": "#<ActionView::TemplateRenderer:0x0000ffffab87fa90>"
      }
    },
    {
      "id": 42,
      "event": "call",
      "thread_id": 4520,
      "defined_class": "ActionView::Resolver",
      "method_id": "find_all",
      "path": "/usr/local/bundle/gems/actionview-7.0.4/lib/action_view/template/resolver.rb",
      "lineno": 62,
      "static": false,
      "parameters": [
        {
          "name": "name",
          "class": "String",
          "object_id": 91580,
          "value": "contact",
          "kind": "req"
        },
        {
          "name": "prefix",
          "class": "String",
          "object_id": 91600,
          "value": "static_pages",
          "kind": "opt"
        },
        {
          "name": "partial",
          "class": "FalseClass",
          "object_id": 0,
          "value": "false",
          "kind": "opt"
        },
        {
          "name": "details",
          "class": "Hash",
          "object_id": 91700,
          "value": "{:locale=>[:en], :formats=>[:html], :variants=>[], :handlers=>[:raw, :erb, :html, :builder, :ruby, :jbuilder]}",
          "kind": "opt",
          "size": 4
        },
        {
          "name": "key",
          "class": "ActionView::TemplateDetails::Requested",
          "object_id": 51860,
          "value": "#<ActionView::TemplateDetails::Requested:0x0000ffffa8abc798>",
          "kind": "opt"
        },
        {
          "name": "locals",
          "class": "Array",
          "object_id": 91720,
          "value": "[]",
          "kind": "opt",
          "size": 0
        }
      ],
      "receiver": {
        "class": "ActionView::FileSystemResolver",
        "object_id": 53980,
        "value": "/app/app/views"
      }
    },
    {
      "id": 43,
      "event": "return",
      "thread_id": 4520,
      "parent_id": 42,
      "elapsed": 0.000010750000001280569,
      "elapsed_instrumentation": 0.00019674999998642306,
      "return_value": {
        "class": "Array",
        "value": "[#<ActionView::Template:0x0000ffffab846ee8>]",
        "object_id": 91740,
        "size": 1
      }
    },
    {
      "id": 44,
      "event": "call",
      "thread_id": 4520,
      "defined_class": "ActionView::Resolver",
      "method_id": "find_all",
      "path": "/usr/local/bundle/gems/actionview-7.0.4/lib/action_view/template/resolver.rb",
      "lineno": 62,
      "static": false,
      "parameters": [
        {
          "name": "name",
          "class": "String",
          "object_id": 91760,
          "value": "static_pages",
          "kind": "req"
        },
        {
          "name": "prefix",
          "class": "String",
          "object_id": 54120,
          "value": "layouts",
          "kind": "opt"
        },
        {
          "name": "partial",
          "class": "FalseClass",
          "object_id": 0,
          "value": "false",
          "kind": "opt"
        },
        {
          "name": "details",
          "class": "Hash",
          "object_id": 91780,
          "value": "{:locale=>[:en], :formats=>[:html], :variants=>[], :handlers=>[:raw, :erb, :html, :builder, :ruby, :jbuilder]}",
          "kind": "opt",
          "size": 4
        },
        {
          "name": "key",
          "class": "ActionView::TemplateDetails::Requested",
          "object_id": 51860,
          "value": "#<ActionView::TemplateDetails::Requested:0x0000ffffa8abc798>",
          "kind": "opt"
        },
        {
          "name": "locals",
          "class": "Array",
          "object_id": 91800,
          "value": "[]",
          "kind": "opt",
          "size": 0
        }
      ],
      "receiver": {
        "class": "ActionView::FileSystemResolver",
        "object_id": 53980,
        "value": "/app/app/views"
      }
    },
    {
      "id": 45,
      "event": "return",
      "thread_id": 4520,
      "parent_id": 44,
      "elapsed": 0.0014045420000456943,
      "elapsed_instrumentation": 0.00009945900001184782,
      "return_value": {
        "class": "Array",
        "value": "[]",
        "object_id": 91820,
        "size": 0
      }
    },
    {
      "id": 46,
      "event": "call",
      "thread_id": 4520,
      "defined_class": "ActionView::Resolver",
      "method_id": "find_all",
      "path": "/usr/local/bundle/gems/actionview-7.0.4/lib/action_view/template/resolver.rb",
      "lineno": 62,
      "static": false,
      "parameters": [
        {
          "name": "name",
          "class": "String",
          "object_id": 91760,
          "value": "static_pages",
          "kind": "req"
        },
        {
          "name": "prefix",
          "class": "String",
          "object_id": 54120,
          "value": "layouts",
          "kind": "opt"
        },
        {
          "name": "partial",
          "class": "FalseClass",
          "object_id": 0,
          "value": "false",
          "kind": "opt"
        },
        {
          "name": "details",
          "class": "Hash",
          "object_id": 91780,
          "value": "{:locale=>[:en], :formats=>[:html], :variants=>[], :handlers=>[:raw, :erb, :html, :builder, :ruby, :jbuilder]}",
          "kind": "opt",
          "size": 4
        },
        {
          "name": "key",
          "class": "ActionView::TemplateDetails::Requested",
          "object_id": 51860,
          "value": "#<ActionView::TemplateDetails::Requested:0x0000ffffa8abc798>",
          "kind": "opt"
        },
        {
          "name": "locals",
          "class": "Array",
          "object_id": 91800,
          "value": "[]",
          "kind": "opt",
          "size": 0
        }
      ],
      "receiver": {
        "class": "ActionView::FileSystemResolver",
        "object_id": 54200,
        "value": "/usr/local/bundle/gems/actiontext-7.0.4/app/views"
      }
    },
    {
      "id": 47,
      "event": "return",
      "thread_id": 4520,
      "parent_id": 46,
      "elapsed": 0.00005783400001746486,
      "elapsed_instrumentation": 0.00010425000004943286,
      "return_value": {
        "class": "Array",
        "value": "[]",
        "object_id": 91840,
        "size": 0
      }
    },
    {
      "id": 48,
      "event": "call",
      "thread_id": 4520,
      "defined_class": "ActionView::Resolver",
      "method_id": "find_all",
      "path": "/usr/local/bundle/gems/actionview-7.0.4/lib/action_view/template/resolver.rb",
      "lineno": 62,
      "static": false,
      "parameters": [
        {
          "name": "name",
          "class": "String",
          "object_id": 91760,
          "value": "static_pages",
          "kind": "req"
        },
        {
          "name": "prefix",
          "class": "String",
          "object_id": 54120,
          "value": "layouts",
          "kind": "opt"
        },
        {
          "name": "partial",
          "class": "FalseClass",
          "object_id": 0,
          "value": "false",
          "kind": "opt"
        },
        {
          "name": "details",
          "class": "Hash",
          "object_id": 91780,
          "value": "{:locale=>[:en], :formats=>[:html], :variants=>[], :handlers=>[:raw, :erb, :html, :builder, :ruby, :jbuilder]}",
          "kind": "opt",
          "size": 4
        },
        {
          "name": "key",
          "class": "ActionView::TemplateDetails::Requested",
          "object_id": 51860,
          "value": "#<ActionView::TemplateDetails::Requested:0x0000ffffa8abc798>",
          "kind": "opt"
        },
        {
          "name": "locals",
          "class": "Array",
          "object_id": 91800,
          "value": "[]",
          "kind": "opt",
          "size": 0
        }
      ],
      "receiver": {
        "class": "ActionView::FileSystemResolver",
        "object_id": 54240,
        "value": "/usr/local/bundle/gems/actionmailbox-7.0.4/app/views"
      }
    },
    {
      "id": 49,
      "event": "return",
      "thread_id": 4520,
      "parent_id": 48,
      "elapsed": 0.000021875000129512046,
      "elapsed_instrumentation": 0.00005991700004415179,
      "return_value": {
        "class": "Array",
        "value": "[]",
        "object_id": 91860,
        "size": 0
      }
    },
    {
      "id": 50,
      "event": "call",
      "thread_id": 4520,
      "defined_class": "ActionView::Resolver",
      "method_id": "find_all",
      "path": "/usr/local/bundle/gems/actionview-7.0.4/lib/action_view/template/resolver.rb",
      "lineno": 62,
      "static": false,
      "parameters": [
        {
          "name": "name",
          "class": "String",
          "object_id": 54280,
          "value": "application",
          "kind": "req"
        },
        {
          "name": "prefix",
          "class": "String",
          "object_id": 54120,
          "value": "layouts",
          "kind": "opt"
        },
        {
          "name": "partial",
          "class": "FalseClass",
          "object_id": 0,
          "value": "false",
          "kind": "opt"
        },
        {
          "name": "details",
          "class": "Hash",
          "object_id": 91880,
          "value": "{:locale=>[:en], :formats=>[:html], :variants=>[], :handlers=>[:raw, :erb, :html, :builder, :ruby, :jbuilder]}",
          "kind": "opt",
          "size": 4
        },
        {
          "name": "key",
          "class": "ActionView::TemplateDetails::Requested",
          "object_id": 51860,
          "value": "#<ActionView::TemplateDetails::Requested:0x0000ffffa8abc798>",
          "kind": "opt"
        },
        {
          "name": "locals",
          "class": "Array",
          "object_id": 91900,
          "value": "[]",
          "kind": "opt",
          "size": 0
        }
      ],
      "receiver": {
        "class": "ActionView::FileSystemResolver",
        "object_id": 53980,
        "value": "/app/app/views"
      }
    },
    {
      "id": 51,
      "event": "return",
      "thread_id": 4520,
      "parent_id": 50,
      "elapsed": 0.000004999999873689376,
      "elapsed_instrumentation": 0.00011466599994491844,
      "return_value": {
        "class": "Array",
        "value": "[#<ActionView::Template:0x0000ffffab4c14a8>]",
        "object_id": 91920,
        "size": 1
      }
    },
    {
      "id": 52,
      "event": "call",
      "thread_id": 4520,
      "defined_class": "Logger::LogDevice",
      "method_id": "write",
      "path": "/usr/local/lib/ruby/3.1.0/logger/log_device.rb",
      "lineno": 31,
      "static": false,
      "parameters": [
        {
          "name": "message",
          "class": "String",
          "object_id": 91940,
          "value": "  Rendering layout layouts/application.html.erb\n",
          "kind": "req"
        }
      ],
      "receiver": {
        "class": "Logger::LogDevice",
        "object_id": 9040,
        "value": "#<Logger::LogDevice:0x0000ffffab8fa588>"
      }
    },
    {
      "id": 53,
      "event": "return",
      "thread_id": 4520,
      "parent_id": 52,
      "elapsed": 0.0005568749998019484,
      "elapsed_instrumentation": 0.00005008400012229686,
      "return_value": {
        "class": "Integer",
        "value": "48",
        "object_id": 97
      }
    },
    {
      "id": 54,
      "event": "call",
      "thread_id": 4520,
      "defined_class": "Logger::LogDevice",
      "method_id": "write",
      "path": "/usr/local/lib/ruby/3.1.0/logger/log_device.rb",
      "lineno": 31,
      "static": false,
      "parameters": [
        {
          "name": "message",
          "class": "String",
          "object_id": 91960,
          "value": "  Rendering static_pages/contact.html.erb within layouts/application\n",
          "kind": "req"
        }
      ],
      "receiver": {
        "class": "Logger::LogDevice",
        "object_id": 9040,
        "value": "#<Logger::LogDevice:0x0000ffffab8fa588>"
      }
    },
    {
      "id": 55,
      "event": "return",
      "thread_id": 4520,
      "parent_id": 54,
      "elapsed": 0.00033195800006069476,
      "elapsed_instrumentation": 0.00004645900003197312,
      "return_value": {
        "class": "Integer",
        "value": "69",
        "object_id": 139
      }
    },
    {
      "id": 56,
      "event": "call",
      "thread_id": 4520,
      "defined_class": "Logger::LogDevice",
      "method_id": "write",
      "path": "/usr/local/lib/ruby/3.1.0/logger/log_device.rb",
      "lineno": 31,
      "static": false,
      "parameters": [
        {
          "name": "message",
          "class": "String",
          "object_id": 92000,
          "value": "  Rendered static_pages/contact.html.erb within layouts/application (Duration: 1.5ms | Allocations:  (...5 more characters)",
          "kind": "req"
        }
      ],
      "receiver": {
        "class": "Logger::LogDevice",
        "object_id": 9040,
        "value": "#<Logger::LogDevice:0x0000ffffab8fa588>"
      }
    },
    {
      "id": 57,
      "event": "return",
      "thread_id": 4520,
      "parent_id": 56,
      "elapsed": 0.0005135000001246226,
      "elapsed_instrumentation": 0.00013804100012748677,
      "return_value": {
        "class": "Integer",
        "value": "105",
        "object_id": 211
      }
    },
    {
      "id": 58,
      "event": "call",
      "thread_id": 4520,
      "defined_class": "ApplicationHelper",
      "method_id": "full_title",
      "path": "app/helpers/application_helper.rb",
      "lineno": 4,
      "static": false,
      "parameters": [
        {
          "name": "page_title",
          "class": "ActiveSupport::SafeBuffer",
          "object_id": 92020,
          "value": "Contact",
          "kind": "opt"
        }
      ],
      "receiver": {
        "class": "ActionView::Base",
        "object_id": 92040,
        "value": "#<#<Class:0x0000ffffab8545e8>:0x0000ffffab878b78>"
      }
    },
    {
      "id": 59,
      "event": "return",
      "thread_id": 4520,
      "parent_id": 58,
      "elapsed": 0.000005458000032376731,
      "elapsed_instrumentation": 0.00015716699977019744,
      "return_value": {
        "class": "String",
        "value": "Contact | Ruby on Rails Tutorial Sample App",
        "object_id": 92060
      }
    },
    {
      "id": 60,
      "event": "call",
      "thread_id": 4520,
      "defined_class": "app_views_layouts__shim_html_erb",
      "method_id": "render",
      "path": "app/views/layouts/_shim.html.erb",
      "static": true,
      "receiver": {
        "class": "ActionView::PartialRenderer",
        "object_id": 92720,
        "value": "#<ActionView::PartialRenderer:0x0000ffffab7379f8>"
      }
    },
    {
      "id": 61,
      "event": "call",
      "thread_id": 4520,
      "defined_class": "ActionView::Resolver",
      "method_id": "find_all",
      "path": "/usr/local/bundle/gems/actionview-7.0.4/lib/action_view/template/resolver.rb",
      "lineno": 62,
      "static": false,
      "parameters": [
        {
          "name": "name",
          "class": "String",
          "object_id": 92080,
          "value": "shim",
          "kind": "req"
        },
        {
          "name": "prefix",
          "class": "String",
          "object_id": 92100,
          "value": "layouts",
          "kind": "opt"
        },
        {
          "name": "partial",
          "class": "TrueClass",
          "object_id": 20,
          "value": "true",
          "kind": "opt"
        },
        {
          "name": "details",
          "class": "Hash",
          "object_id": 91700,
          "value": "{:locale=>[:en], :formats=>[:html], :variants=>[], :handlers=>[:raw, :erb, :html, :builder, :ruby, :jbuilder]}",
          "kind": "opt",
          "size": 4
        },
        {
          "name": "key",
          "class": "ActionView::TemplateDetails::Requested",
          "object_id": 51860,
          "value": "#<ActionView::TemplateDetails::Requested:0x0000ffffa8abc798>",
          "kind": "opt"
        },
        {
          "name": "locals",
          "class": "Array",
          "object_id": 92120,
          "value": "[]",
          "kind": "opt",
          "size": 0
        }
      ],
      "receiver": {
        "class": "ActionView::FileSystemResolver",
        "object_id": 53980,
        "value": "/app/app/views"
      }
    },
    {
      "id": 62,
      "event": "return",
      "thread_id": 4520,
      "parent_id": 61,
      "elapsed": 0.000017374999970343197,
      "elapsed_instrumentation": 0.00022920800006431818,
      "return_value": {
        "class": "Array",
        "value": "[#<ActionView::Template:0x0000ffffa9dfdf78>]",
        "object_id": 92140,
        "size": 1
      }
    },
    {
      "id": 63,
      "event": "call",
      "thread_id": 4520,
      "defined_class": "Logger::LogDevice",
      "method_id": "write",
      "path": "/usr/local/lib/ruby/3.1.0/logger/log_device.rb",
      "lineno": 31,
      "static": false,
      "parameters": [
        {
          "name": "message",
          "class": "String",
          "object_id": 92160,
          "value": "  Rendered layouts/_shim.html.erb (Duration: 0.0ms | Allocations: 19)\n",
          "kind": "req"
        }
      ],
      "receiver": {
        "class": "Logger::LogDevice",
        "object_id": 9040,
        "value": "#<Logger::LogDevice:0x0000ffffab8fa588>"
      }
    },
    {
      "id": 64,
      "event": "return",
      "thread_id": 4520,
      "parent_id": 63,
      "elapsed": 0.0007430839998505689,
      "elapsed_instrumentation": 0.00006483399988610472,
      "return_value": {
        "class": "Integer",
        "value": "70",
        "object_id": 141
      }
    },
    {
      "id": 65,
      "event": "return",
      "thread_id": 4520,
      "parent_id": 60,
      "elapsed": 0.0011968329999945126,
      "elapsed_instrumentation": 0.000031917000114844996
    },
    {
      "id": 66,
      "event": "call",
      "thread_id": 4520,
      "defined_class": "app_views_layouts__header_html_erb",
      "method_id": "render",
      "path": "app/views/layouts/_header.html.erb",
      "static": true,
      "receiver": {
        "class": "ActionView::PartialRenderer",
        "object_id": 92740,
        "value": "#<ActionView::PartialRenderer:0x0000ffffab753040>"
      }
    },
    {
      "id": 67,
      "event": "call",
      "thread_id": 4520,
      "defined_class": "ActionView::Resolver",
      "method_id": "find_all",
      "path": "/usr/local/bundle/gems/actionview-7.0.4/lib/action_view/template/resolver.rb",
      "lineno": 62,
      "static": false,
      "parameters": [
        {
          "name": "name",
          "class": "String",
          "object_id": 92180,
          "value": "header",
          "kind": "req"
        },
        {
          "name": "prefix",
          "class": "String",
          "object_id": 92200,
          "value": "layouts",
          "kind": "opt"
        },
        {
          "name": "partial",
          "class": "TrueClass",
          "object_id": 20,
          "value": "true",
          "kind": "opt"
        },
        {
          "name": "details",
          "class": "Hash",
          "object_id": 91700,
          "value": "{:locale=>[:en], :formats=>[:html], :variants=>[], :handlers=>[:raw, :erb, :html, :builder, :ruby, :jbuilder]}",
          "kind": "opt",
          "size": 4
        },
        {
          "name": "key",
          "class": "ActionView::TemplateDetails::Requested",
          "object_id": 51860,
          "value": "#<ActionView::TemplateDetails::Requested:0x0000ffffa8abc798>",
          "kind": "opt"
        },
        {
          "name": "locals",
          "class": "Array",
          "object_id": 92220,
          "value": "[]",
          "kind": "opt",
          "size": 0
        }
      ],
      "receiver": {
        "class": "ActionView::FileSystemResolver",
        "object_id": 53980,
        "value": "/app/app/views"
      }
    },
    {
      "id": 68,
      "event": "return",
      "thread_id": 4520,
      "parent_id": 67,
      "elapsed": 0.000012666999964494607,
      "elapsed_instrumentation": 0.00019320899991726037,
      "return_value": {
        "class": "Array",
        "value": "[#<ActionView::Template:0x0000ffffa9e07348>]",
        "object_id": 92240,
        "size": 1
      }
    },
    {
      "id": 69,
      "event": "call",
      "thread_id": 4520,
      "defined_class": "SessionsHelper",
      "method_id": "logged_in?",
      "path": "app/helpers/sessions_helper.rb",
      "lineno": 40,
      "static": false,
      "receiver": {
        "class": "ActionView::Base",
        "object_id": 92040,
        "value": "#<#<Class:0x0000ffffab8545e8>:0x0000ffffab878b78>"
      }
    },
    {
      "id": 70,
      "event": "call",
      "thread_id": 4520,
      "defined_class": "SessionsHelper",
      "method_id": "current_user",
      "path": "app/helpers/sessions_helper.rb",
      "lineno": 19,
      "static": false,
      "receiver": {
        "class": "ActionView::Base",
        "object_id": 92040,
        "value": "#<#<Class:0x0000ffffab8545e8>:0x0000ffffab878b78>"
      }
    },
    {
      "id": 71,
      "event": "call",
      "thread_id": 4520,
      "defined_class": "ActionDispatch::Request::Session",
      "method_id": "[]",
      "path": "/usr/local/bundle/gems/actionpack-7.0.4/lib/action_dispatch/request/session.rb",
      "lineno": 110,
      "static": false,
      "parameters": [
        {
          "name": "key",
          "class": "Symbol",
          "object_id": 3069788,
          "value": ":user_id",
          "kind": "req"
        }
      ],
      "receiver": {
        "class": "ActionDispatch::Request::Session",
        "object_id": 92260,
        "value": "#<ActionDispatch::Request::Session:0x0000ffffab8b0c30>"
      }
    },
    {
      "id": 72,
      "event": "call",
      "thread_id": 4520,
      "defined_class": "ActionDispatch::Cookies::CookieJar",
      "method_id": "update",
      "path": "/usr/local/bundle/gems/actionpack-7.0.4/lib/action_dispatch/middleware/cookies.rb",
      "lineno": 352,
      "static": false,
      "parameters": [
        {
          "name": "other_hash",
          "class": "Hash",
          "object_id": 92280,
          "value": "{}",
          "kind": "req",
          "size": 0
        }
      ],
      "receiver": {
        "class": "ActionDispatch::Cookies::CookieJar",
        "object_id": 92300,
        "value": "#<ActionDispatch::Cookies::CookieJar:0x0000ffffab76fee8>"
      }
    },
    {
      "id": 73,
      "event": "return",
      "thread_id": 4520,
      "parent_id": 72,
      "elapsed": 0.000016040999980759807,
      "elapsed_instrumentation": 0.00003245800007789512,
      "return_value": {
        "class": "ActionDispatch::Cookies::CookieJar",
        "value": "#<ActionDispatch::Cookies::CookieJar:0x0000ffffab76fee8>",
        "object_id": 92300
      }
    },
    {
      "id": 74,
      "event": "call",
      "thread_id": 4520,
      "defined_class": "ActionDispatch::Cookies::CookieJar",
      "method_id": "[]",
      "path": "/usr/local/bundle/gems/actionpack-7.0.4/lib/action_dispatch/middleware/cookies.rb",
      "lineno": 336,
      "static": false,
      "parameters": [
        {
          "name": "name",
          "class": "String",
          "object_id": 52740,
          "value": "_sample_app_session",
          "kind": "req"
        }
      ],
      "receiver": {
        "class": "ActionDispatch::Cookies::CookieJar",
        "object_id": 92300,
        "value": "#<ActionDispatch::Cookies::CookieJar:0x0000ffffab76fee8>"
      }
    },
    {
      "id": 75,
      "event": "return",
      "thread_id": 4520,
      "parent_id": 74,
      "elapsed": 0.0000019159999737894395,
      "elapsed_instrumentation": 0.0000708749998921121
    },
    {
      "id": 76,
      "event": "return",
      "thread_id": 4520,
      "parent_id": 71,
      "elapsed": 0.0004853330001424183,
      "elapsed_instrumentation": 0.00002033400005529984
    },
    {
      "id": 77,
      "event": "call",
      "thread_id": 4520,
      "defined_class": "ActionDispatch::Cookies::CookieJar",
      "method_id": "[]",
      "path": "/usr/local/bundle/gems/actionpack-7.0.4/lib/action_dispatch/middleware/cookies.rb",
      "lineno": 336,
      "static": false,
      "parameters": [
        {
          "name": "name",
          "class": "String",
          "object_id": 92320,
          "value": "user_id",
          "kind": "req"
        }
      ],
      "receiver": {
        "class": "ActionDispatch::Cookies::CookieJar",
        "object_id": 92300,
        "value": "#<ActionDispatch::Cookies::CookieJar:0x0000ffffab76fee8>"
      }
    },
    {
      "id": 78,
      "event": "return",
      "thread_id": 4520,
      "parent_id": 77,
      "elapsed": 6.669999947916949e-7,
      "elapsed_instrumentation": 0.000027374999945095624
    },
    {
      "id": 79,
      "event": "return",
      "thread_id": 4520,
      "parent_id": 70,
      "elapsed": 0.0005728339999677701,
      "elapsed_instrumentation": 0.000014833000022917986
    },
    {
      "id": 80,
      "event": "return",
      "thread_id": 4520,
      "parent_id": 69,
      "elapsed": 0.0005970830000023852,
      "elapsed_instrumentation": 0.00004558399996312801
    },
    {
      "id": 81,
      "event": "call",
      "thread_id": 4520,
      "defined_class": "Logger::LogDevice",
      "method_id": "write",
      "path": "/usr/local/lib/ruby/3.1.0/logger/log_device.rb",
      "lineno": 31,
      "static": false,
      "parameters": [
        {
          "name": "message",
          "class": "String",
          "object_id": 92340,
          "value": "  Rendered layouts/_header.html.erb (Duration: 0.9ms | Allocations: 740)\n",
          "kind": "req"
        }
      ],
      "receiver": {
        "class": "Logger::LogDevice",
        "object_id": 9040,
        "value": "#<Logger::LogDevice:0x0000ffffab8fa588>"
      }
    },
    {
      "id": 82,
      "event": "return",
      "thread_id": 4520,
      "parent_id": 81,
      "elapsed": 0.000523416000078214,
      "elapsed_instrumentation": 0.00005012500014345278,
      "return_value": {
        "class": "Integer",
        "value": "73",
        "object_id": 147
      }
    },
    {
      "id": 83,
      "event": "return",
      "thread_id": 4520,
      "parent_id": 66,
      "elapsed": 0.001798959000097966,
      "elapsed_instrumentation": 0.00003012499996657425
    },
    {
      "id": 84,
      "event": "call",
      "thread_id": 4520,
      "defined_class": "ActionDispatch::Request::Session",
      "method_id": "[]",
      "path": "/usr/local/bundle/gems/actionpack-7.0.4/lib/action_dispatch/request/session.rb",
      "lineno": 110,
      "static": false,
      "parameters": [
        {
          "name": "key",
          "class": "String",
          "object_id": 52440,
          "value": "flash",
          "kind": "req"
        }
      ],
      "receiver": {
        "class": "ActionDispatch::Request::Session",
        "object_id": 92260,
        "value": "#<ActionDispatch::Request::Session:0x0000ffffab8b0c30>"
      }
    },
    {
      "id": 85,
      "event": "return",
      "thread_id": 4520,
      "parent_id": 84,
      "elapsed": 0.00006454200001826393,
      "elapsed_instrumentation": 0.000049458000148661085
    },
    {
      "id": 86,
      "event": "call",
      "thread_id": 4520,
      "defined_class": "app_views_layouts__footer_html_erb",
      "method_id": "render",
      "path": "app/views/layouts/_footer.html.erb",
      "static": true,
      "receiver": {
        "class": "ActionView::PartialRenderer",
        "object_id": 92760,
        "value": "#<ActionView::PartialRenderer:0x0000ffffab4d12e0>"
      }
    },
    {
      "id": 87,
      "event": "call",
      "thread_id": 4520,
      "defined_class": "ActionView::Resolver",
      "method_id": "find_all",
      "path": "/usr/local/bundle/gems/actionview-7.0.4/lib/action_view/template/resolver.rb",
      "lineno": 62,
      "static": false,
      "parameters": [
        {
          "name": "name",
          "class": "String",
          "object_id": 92360,
          "value": "footer",
          "kind": "req"
        },
        {
          "name": "prefix",
          "class": "String",
          "object_id": 92380,
          "value": "layouts",
          "kind": "opt"
        },
        {
          "name": "partial",
          "class": "TrueClass",
          "object_id": 20,
          "value": "true",
          "kind": "opt"
        },
        {
          "name": "details",
          "class": "Hash",
          "object_id": 91700,
          "value": "{:locale=>[:en], :formats=>[:html], :variants=>[], :handlers=>[:raw, :erb, :html, :builder, :ruby, :jbuilder]}",
          "kind": "opt",
          "size": 4
        },
        {
          "name": "key",
          "class": "ActionView::TemplateDetails::Requested",
          "object_id": 51860,
          "value": "#<ActionView::TemplateDetails::Requested:0x0000ffffa8abc798>",
          "kind": "opt"
        },
        {
          "name": "locals",
          "class": "Array",
          "object_id": 92400,
          "value": "[]",
          "kind": "opt",
          "size": 0
        }
      ],
      "receiver": {
        "class": "ActionView::FileSystemResolver",
        "object_id": 53980,
        "value": "/app/app/views"
      }
    },
    {
      "id": 88,
      "event": "return",
      "thread_id": 4520,
      "parent_id": 87,
      "elapsed": 0.0000162080000336573,
      "elapsed_instrumentation": 0.00018554100006440422,
      "return_value": {
        "class": "Array",
        "value": "[#<ActionView::Template:0x0000ffffa9dc9660>]",
        "object_id": 92420,
        "size": 1
      }
    },
    {
      "id": 89,
      "event": "call",
      "thread_id": 4520,
      "defined_class": "Logger::LogDevice",
      "method_id": "write",
      "path": "/usr/local/lib/ruby/3.1.0/logger/log_device.rb",
      "lineno": 31,
      "static": false,
      "parameters": [
        {
          "name": "message",
          "class": "String",
          "object_id": 92440,
          "value": "  Rendered layouts/_footer.html.erb (Duration: 0.1ms | Allocations: 74)\n",
          "kind": "req"
        }
      ],
      "receiver": {
        "class": "Logger::LogDevice",
        "object_id": 9040,
        "value": "#<Logger::LogDevice:0x0000ffffab8fa588>"
      }
    },
    {
      "id": 90,
      "event": "return",
      "thread_id": 4520,
      "parent_id": 89,
      "elapsed": 0.00246220799999719,
      "elapsed_instrumentation": 0.00007058400024106959,
      "return_value": {
        "class": "Integer",
        "value": "72",
        "object_id": 145
      }
    },
    {
      "id": 91,
      "event": "return",
      "thread_id": 4520,
      "parent_id": 86,
      "elapsed": 0.0029684579999411653,
      "elapsed_instrumentation": 0.000030917000003682915
    },
    {
      "id": 92,
      "event": "call",
      "thread_id": 4520,
      "defined_class": "Logger::LogDevice",
      "method_id": "write",
      "path": "/usr/local/lib/ruby/3.1.0/logger/log_device.rb",
      "lineno": 31,
      "static": false,
      "parameters": [
        {
          "name": "message",
          "class": "String",
          "object_id": 92460,
          "value": "  Rendered layout layouts/application.html.erb (Duration: 10.7ms | Allocations: 4275)\n",
          "kind": "req"
        }
      ],
      "receiver": {
        "class": "Logger::LogDevice",
        "object_id": 9040,
        "value": "#<Logger::LogDevice:0x0000ffffab8fa588>"
      }
    },
    {
      "id": 93,
      "event": "return",
      "thread_id": 4520,
      "parent_id": 92,
      "elapsed": 0.001077333000012004,
      "elapsed_instrumentation": 0.00034341700006734754,
      "return_value": {
        "class": "Integer",
        "value": "86",
        "object_id": 173
      }
    },
    {
      "id": 94,
      "event": "return",
      "thread_id": 4520,
      "parent_id": 41,
      "elapsed": 0.015060957999821767,
      "elapsed_instrumentation": 0.000040750000152911525
    },
    {
      "id": 95,
      "event": "return",
      "thread_id": 4520,
      "parent_id": 40,
      "elapsed": 0.015894417000026806,
      "elapsed_instrumentation": 0.00012029100025756634,
      "return_value": {
        "class": "ActionView::OutputBuffer",
        "value": "<!DOCTYPE html>\n<html>\n  <head>\n    <title>Contact | Ruby on Rails Tutorial Sample App</title>\n    < (...3646 more characters)",
        "object_id": 92480
      }
    },
    {
      "id": 96,
      "event": "call",
      "thread_id": 4520,
      "defined_class": "ActiveSupport::Callbacks::CallbackSequence",
      "method_id": "invoke_after",
      "path": "/usr/local/bundle/gems/activesupport-7.0.4/lib/active_support/callbacks.rb",
      "lineno": 598,
      "static": false,
      "parameters": [
        {
          "name": "arg",
          "class": "ActiveSupport::Callbacks::Filters::Environment",
          "object_id": 91460,
          "value": null,
          "kind": "req"
        }
      ],
      "receiver": {
        "class": "ActiveSupport::Callbacks::CallbackSequence",
        "object_id": 91520,
        "value": "#<ActiveSupport::Callbacks::CallbackSequence:0x0000ffffab7fe8c8>"
      }
    },
    {
      "id": 97,
      "event": "return",
      "thread_id": 4520,
      "parent_id": 96,
      "elapsed": 0.000001582999857419054,
      "elapsed_instrumentation": 0.00005362599995351047,
      "return_value": {
        "class": "Array",
        "value": "[]",
        "object_id": 92500,
        "size": 0
      }
    },
    {
      "id": 98,
      "event": "call",
      "thread_id": 4520,
      "defined_class": "ActiveSupport::Callbacks::CallbackSequence",
      "method_id": "invoke_after",
      "path": "/usr/local/bundle/gems/activesupport-7.0.4/lib/active_support/callbacks.rb",
      "lineno": 598,
      "static": false,
      "parameters": [
        {
          "name": "arg",
          "class": "ActiveSupport::Callbacks::Filters::Environment",
          "object_id": 91460,
          "value": null,
          "kind": "req"
        }
      ],
      "receiver": {
        "class": "ActiveSupport::Callbacks::CallbackSequence",
        "object_id": 91480,
        "value": "#<ActiveSupport::Callbacks::CallbackSequence:0x0000ffffab7fe058>"
      }
    },
    {
      "id": 99,
      "event": "return",
      "thread_id": 4520,
      "parent_id": 98,
      "elapsed": 0.000023124999870560714,
      "elapsed_instrumentation": 0.000035750000051848474,
      "return_value": {
        "class": "Array",
        "value": "[#<Proc:0x0000ffffab7fd9c8 /usr/local/bundle/gems/activesupport-7.0.4/lib/active_support/callbacks.rb]",
        "object_id": 92520,
        "size": 1
      }
    },
    {
      "id": 100,
      "event": "call",
      "thread_id": 4520,
      "defined_class": "Logger::LogDevice",
      "method_id": "write",
      "path": "/usr/local/lib/ruby/3.1.0/logger/log_device.rb",
      "lineno": 31,
      "static": false,
      "parameters": [
        {
          "name": "message",
          "class": "String",
          "object_id": 92540,
          "value": "Completed 200 OK in 24ms (Views: 16.2ms | ActiveRecord: 0.0ms | Allocations: 7521)\n",
          "kind": "req"
        }
      ],
      "receiver": {
        "class": "Logger::LogDevice",
        "object_id": 9040,
        "value": "#<Logger::LogDevice:0x0000ffffab8fa588>"
      }
    },
    {
      "id": 101,
      "event": "return",
      "thread_id": 4520,
      "parent_id": 100,
      "elapsed": 0.0016677920000347513,
      "elapsed_instrumentation": 0.00006808299963267928,
      "return_value": {
        "class": "Integer",
        "value": "83",
        "object_id": 167
      }
    },
    {
      "id": 102,
      "event": "return",
      "thread_id": 4520,
      "parent_id": 21,
      "elapsed": 0.033841375000065455,
      "elapsed_instrumentation": 0.00044549899985213415,
      "http_server_response": {
        "status_code": 200,
        "headers": {
          "X-Frame-Options": "SAMEORIGIN",
          "X-XSS-Protection": "0",
          "X-Content-Type-Options": "nosniff",
          "X-Download-Options": "noopen",
          "X-Permitted-Cross-Domain-Policies": "none",
          "Referrer-Policy": "strict-origin-when-cross-origin",
          "Link": "</assets/application-cdc3bed7911b8306994a416a4c2682e340e553fd434035cdc35c53e1200df70a.css>; rel=preload; as=style; nopush,</assets/es-module-shims.min-606ae9c3279013fe751cee30f719a592f759e705edb66496812f3d9dbce3d850.js>; rel=preload; as=script; nopush",
          "Content-Type": "text/html; charset=utf-8",
          "ETag": "W/\"6afeb21e13e50bd62ace9cc2719a144f\"",
          "Cache-Control": "max-age=0, private, must-revalidate",
          "X-Request-Id": "376514b6-6fd5-415d-83c5-480cf04bca10",
          "X-Runtime": "0.033411"
        }
      }
    },
    {
      "id": 103,
      "event": "call",
      "thread_id": 4520,
      "defined_class": "ActiveSupport::Callbacks::CallbackSequence",
      "method_id": "invoke_before",
      "path": "/usr/local/bundle/gems/activesupport-7.0.4/lib/active_support/callbacks.rb",
      "lineno": 594,
      "static": false,
      "parameters": [
        {
          "name": "arg",
          "class": "ActiveSupport::Callbacks::Filters::Environment",
          "object_id": 92580,
          "value": null,
          "kind": "req"
        }
      ],
      "receiver": {
        "class": "ActiveSupport::Callbacks::CallbackSequence",
        "object_id": 53520,
        "value": "#<ActiveSupport::Callbacks::CallbackSequence:0x0000ffffab74eb58>"
      }
    },
    {
      "id": 104,
      "event": "return",
      "thread_id": 4520,
      "parent_id": 103,
      "elapsed": 0.00008041699993555085,
      "elapsed_instrumentation": 0.00008091700010481873,
      "return_value": {
        "class": "Array",
        "value": "[#<Proc:0x0000ffffab74d758 /usr/local/bundle/gems/activesupport-7.0.4/lib/active_support/callbacks.rb, #<Proc:0x0000ffffab74d960 /usr/local/bundle/gems/activesupport-7.0.4/lib/active_support/callbacks.rb, #<Proc:0x0000ffffab74dc58 /usr/local/bundle/gems/activesupport-7.0.4/lib/active_support/callbacks.rb, #<Proc:0x0000ffffab74dfc8 /usr/local/bundle/gems/activesupport-7.0.4/lib/active_support/callbacks.rb]",
        "object_id": 53540,
        "size": 4
      }
    },
    {
      "id": 105,
      "event": "call",
      "thread_id": 4520,
      "defined_class": "ActiveSupport::Callbacks::CallbackSequence",
      "method_id": "invoke_after",
      "path": "/usr/local/bundle/gems/activesupport-7.0.4/lib/active_support/callbacks.rb",
      "lineno": 598,
      "static": false,
      "parameters": [
        {
          "name": "arg",
          "class": "ActiveSupport::Callbacks::Filters::Environment",
          "object_id": 92580,
          "value": null,
          "kind": "req"
        }
      ],
      "receiver": {
        "class": "ActiveSupport::Callbacks::CallbackSequence",
        "object_id": 53520,
        "value": "#<ActiveSupport::Callbacks::CallbackSequence:0x0000ffffab74eb58>"
      }
    },
    {
      "id": 106,
      "event": "return",
      "thread_id": 4520,
      "parent_id": 105,
      "elapsed": 0.000011458000017228187,
      "elapsed_instrumentation": 0.000027625000029729563,
      "return_value": {
        "class": "Array",
        "value": "[#<Proc:0x0000ffffab74e1d0 /usr/local/bundle/gems/activesupport-7.0.4/lib/active_support/callbacks.rb]",
        "object_id": 53560,
        "size": 1
      }
    },
    {
      "id": 107,
      "event": "call",
      "thread_id": 4520,
      "defined_class": "ActiveSupport::Callbacks::CallbackSequence",
      "method_id": "invoke_before",
      "path": "/usr/local/bundle/gems/activesupport-7.0.4/lib/active_support/callbacks.rb",
      "lineno": 594,
      "static": false,
      "parameters": [
        {
          "name": "arg",
          "class": "ActiveSupport::Callbacks::Filters::Environment",
          "object_id": 92640,
          "value": null,
          "kind": "req"
        }
      ],
      "receiver": {
        "class": "ActiveSupport::Callbacks::CallbackSequence",
        "object_id": 90800,
        "value": "#<ActiveSupport::Callbacks::CallbackSequence:0x0000ffffa9dc6028>"
      }
    },
    {
      "id": 108,
      "event": "return",
      "thread_id": 4520,
      "parent_id": 107,
      "elapsed": 0.0000011669999366858974,
      "elapsed_instrumentation": 0.00007612400008838449,
      "return_value": {
        "class": "Array",
        "value": "[]",
        "object_id": 90820,
        "size": 0
      }
    },
    {
      "id": 109,
      "event": "call",
      "thread_id": 4520,
      "defined_class": "ActiveSupport::Callbacks::CallbackSequence",
      "method_id": "invoke_after",
      "path": "/usr/local/bundle/gems/activesupport-7.0.4/lib/active_support/callbacks.rb",
      "lineno": 598,
      "static": false,
      "parameters": [
        {
          "name": "arg",
          "class": "ActiveSupport::Callbacks::Filters::Environment",
          "object_id": 92640,
          "value": null,
          "kind": "req"
        }
      ],
      "receiver": {
        "class": "ActiveSupport::Callbacks::CallbackSequence",
        "object_id": 90800,
        "value": "#<ActiveSupport::Callbacks::CallbackSequence:0x0000ffffa9dc6028>"
      }
    },
    {
      "id": 110,
      "event": "return",
      "thread_id": 4520,
      "parent_id": 109,
      "elapsed": 0.00004616599994733406,
      "elapsed_instrumentation": 0.000037916999872322776,
      "return_value": {
        "class": "Array",
        "value": "[#<Proc:0x0000ffffa9dc5d80 /usr/local/bundle/gems/activesupport-7.0.4/lib/active_support/callbacks.rb, #<Proc:0x0000ffffa9dc5c40 /usr/local/bundle/gems/activesupport-7.0.4/lib/active_support/callbacks.rb]",
        "object_id": 90840,
        "size": 2
      }
    },
    {
      "id": 111,
      "event": "call",
      "thread_id": 4520,
      "defined_class": "Logger::LogDevice",
      "method_id": "write",
      "path": "/usr/local/lib/ruby/3.1.0/logger/log_device.rb",
      "lineno": 31,
      "static": false,
      "parameters": [
        {
          "name": "message",
          "class": "String",
          "object_id": 92660,
          "value": "  \u001b[1m\u001b[36mTRANSACTION (0.1ms)\u001b[0m  \u001b[1m\u001b[31mrollback transaction\u001b[0m\n",
          "kind": "req"
        }
      ],
      "receiver": {
        "class": "Logger::LogDevice",
        "object_id": 9040,
        "value": "#<Logger::LogDevice:0x0000ffffab8fa588>"
      }
    },
    {
      "id": 112,
      "event": "return",
      "thread_id": 4520,
      "parent_id": 111,
      "elapsed": 0.002321124999980384,
      "elapsed_instrumentation": 0.00019250000013926183,
      "return_value": {
        "class": "Integer",
        "value": "70",
        "object_id": 141
      }
    },
    {
      "id": 113,
      "event": "call",
      "thread_id": 4520,
      "sql_query": {
        "sql": "rollback transaction",
        "database_type": "sqlite"
      }
    },
    {
      "id": 114,
      "event": "return",
      "thread_id": 4520,
      "parent_id": 113,
      "elapsed": 0.00265775,
      "elapsed_instrumentation": 0.00008316699995702947
    },
    {
      "id": 115,
      "event": "call",
      "thread_id": 4520,
      "defined_class": "ActiveSupport::Callbacks::CallbackSequence",
      "method_id": "invoke_before",
      "path": "/usr/local/bundle/gems/activesupport-7.0.4/lib/active_support/callbacks.rb",
      "lineno": 594,
      "static": false,
      "parameters": [
        {
          "name": "arg",
          "class": "ActiveSupport::Callbacks::Filters::Environment",
          "object_id": 92680,
          "value": null,
          "kind": "req"
        }
      ],
      "receiver": {
        "class": "ActiveSupport::Callbacks::CallbackSequence",
        "object_id": 90900,
        "value": "#<ActiveSupport::Callbacks::CallbackSequence:0x0000ffffab7824a8>"
      }
    },
    {
      "id": 116,
      "event": "return",
      "thread_id": 4520,
      "parent_id": 115,
      "elapsed": 0.000001416000031895237,
      "elapsed_instrumentation": 0.00006104199997025717,
      "return_value": {
        "class": "Array",
        "value": "[]",
        "object_id": 90920,
        "size": 0
      }
    },
    {
      "id": 117,
      "event": "call",
      "thread_id": 4520,
      "defined_class": "ActiveSupport::Callbacks::CallbackSequence",
      "method_id": "invoke_after",
      "path": "/usr/local/bundle/gems/activesupport-7.0.4/lib/active_support/callbacks.rb",
      "lineno": 598,
      "static": false,
      "parameters": [
        {
          "name": "arg",
          "class": "ActiveSupport::Callbacks::Filters::Environment",
          "object_id": 92680,
          "value": null,
          "kind": "req"
        }
      ],
      "receiver": {
        "class": "ActiveSupport::Callbacks::CallbackSequence",
        "object_id": 90900,
        "value": "#<ActiveSupport::Callbacks::CallbackSequence:0x0000ffffab7824a8>"
      }
    },
    {
      "id": 118,
      "event": "return",
      "thread_id": 4520,
      "parent_id": 117,
      "elapsed": 0.000011332999974911218,
      "elapsed_instrumentation": 0.00003708299982463359,
      "return_value": {
        "class": "Array",
        "value": "[#<Proc:0x0000ffffab782138 /usr/local/bundle/gems/activesupport-7.0.4/lib/active_support/callbacks.rb, #<Proc:0x0000ffffab781fd0 /usr/local/bundle/gems/activesupport-7.0.4/lib/active_support/callbacks.rb]",
        "object_id": 90940,
        "size": 2
      }
    }
  ],
  "version": "1.12.0",
  "metadata": {
    "app": "sample_rails_app",
    "language": {
      "name": "ruby",
      "engine": "ruby",
      "version": "3.1.2"
    },
    "client": {
      "name": "appmap",
      "url": "https://github.com/applandinc/appmap-ruby",
      "version": "0.102.2"
    },
    "frameworks": [
      {
        "name": "rails",
        "version": "7.0.4"
      },
      {
        "name": "minitest",
        "version": "5.15.0"
      }
    ],
    "git": {
      "repository": "https://github.com/land-of-apps/sample_rails_app.git",
      "branch": "appmap-configured",
      "commit": "e176455318c46ff6f7cc9d3e547b64c34c903efe",
      "git_last_annotated_tag": null,
      "git_last_tag": null,
      "git_commits_since_last_annotated_tag": null,
      "git_commits_since_last_tag": null
    },
    "name": "Static_pages_controller should get contact",
    "source_location": "test/controllers/static_pages_controller_test.rb:23",
    "recorder": {
      "name": "minitest",
      "type": "tests"
    },
    "test_status": "succeeded"
  },
  "classMap": [
    {
      "name": "actionpack",
      "type": "package",
      "children": [
        {
          "name": "ActionDispatch",
          "type": "class",
          "children": [
            {
              "name": "Integration",
              "type": "class",
              "children": [
                {
                  "name": "Runner",
                  "type": "class",
                  "children": [
                    {
                      "name": "before_setup",
                      "type": "function",
                      "labels": [
                        "deserialize.safe",
                        "lang.eval.safe"
                      ],
                      "static": false,
                      "location": "/usr/local/bundle/gems/actionpack-7.0.4/lib/action_dispatch/testing/integration.rb:329"
                    }
                  ]
                }
              ]
            },
            {
              "name": "Request",
              "type": "class",
              "children": [
                {
                  "name": "Session",
                  "type": "class",
                  "children": [
                    {
                      "name": "[]",
                      "type": "function",
                      "labels": [
                        "http.session.read"
                      ],
                      "static": false,
                      "location": "/usr/local/bundle/gems/actionpack-7.0.4/lib/action_dispatch/request/session.rb:110"
                    }
                  ]
                }
              ]
            },
            {
              "name": "Cookies",
              "type": "class",
              "children": [
                {
                  "name": "CookieJar",
                  "type": "class",
                  "children": [
                    {
                      "name": "update",
                      "type": "function",
                      "labels": [
                        "http.session.write"
                      ],
                      "static": false,
                      "location": "/usr/local/bundle/gems/actionpack-7.0.4/lib/action_dispatch/middleware/cookies.rb:352"
                    },
                    {
                      "name": "[]",
                      "type": "function",
                      "labels": [
                        "http.session.read"
                      ],
                      "static": false,
                      "location": "/usr/local/bundle/gems/actionpack-7.0.4/lib/action_dispatch/middleware/cookies.rb:336"
                    }
                  ]
                }
              ]
            }
          ]
        },
        {
          "name": "ActionController",
          "type": "class",
          "children": [
            {
              "name": "Renderers",
              "type": "class",
              "children": [
                {
                  "name": "render_to_body",
                  "type": "function",
                  "labels": [
                    "mvc.render"
                  ],
                  "static": false,
                  "location": "/usr/local/bundle/gems/actionpack-7.0.4/lib/action_controller/metal/renderers.rb:140"
                }
              ]
            }
          ]
        }
      ]
    },
    {
      "name": "activesupport",
      "type": "package",
      "children": [
        {
          "name": "ActiveSupport",
          "type": "class",
          "children": [
            {
              "name": "Callbacks",
              "type": "class",
              "children": [
                {
                  "name": "CallbackSequence",
                  "type": "class",
                  "children": [
                    {
                      "name": "invoke_before",
                      "type": "function",
                      "labels": [
                        "mvc.before_action"
                      ],
                      "static": false,
                      "location": "/usr/local/bundle/gems/activesupport-7.0.4/lib/active_support/callbacks.rb:594"
                    },
                    {
                      "name": "invoke_after",
                      "type": "function",
                      "labels": [
                        "mvc.after_action"
                      ],
                      "static": false,
                      "location": "/usr/local/bundle/gems/activesupport-7.0.4/lib/active_support/callbacks.rb:598"
                    }
                  ]
                }
              ]
            }
          ]
        }
      ]
    },
    {
      "name": "logger",
      "type": "package",
      "children": [
        {
          "name": "Logger",
          "type": "class",
          "children": [
            {
              "name": "LogDevice",
              "type": "class",
              "children": [
                {
                  "name": "write",
                  "type": "function",
                  "labels": [
                    "log"
                  ],
                  "static": false,
                  "location": "/usr/local/lib/ruby/3.1.0/logger/log_device.rb:31"
                }
              ]
            }
          ]
        }
      ]
    },
    {
      "name": "ruby",
      "type": "package",
      "children": [
        {
          "name": "String",
          "type": "class",
          "children": [
            {
              "name": "unpack",
              "type": "function",
              "labels": [
                "string.unpack"
              ],
              "static": false,
              "location": "<internal:pack>:275"
            }
          ]
        }
      ]
    },
    {
      "name": "app",
      "type": "package",
      "children": [
        {
          "name": "controllers",
          "type": "package",
          "children": [
            {
              "name": "StaticPagesController",
              "type": "class",
              "children": [
                {
                  "name": "contact",
                  "type": "function",
                  "static": false,
                  "location": "app/controllers/static_pages_controller.rb:16"
                }
              ]
            }
          ]
        },
        {
          "name": "views",
          "type": "package",
          "children": [
            {
              "name": "app_views_static_pages_contact_html_erb",
              "type": "class",
              "children": [
                {
                  "name": "render",
                  "type": "function",
                  "labels": [
                    "mvc.template"
                  ],
                  "static": true,
                  "location": "app/views/static_pages/contact.html.erb"
                }
              ]
            },
            {
              "name": "app_views_layouts__shim_html_erb",
              "type": "class",
              "children": [
                {
                  "name": "render",
                  "type": "function",
                  "labels": [
                    "mvc.template"
                  ],
                  "static": true,
                  "location": "app/views/layouts/_shim.html.erb"
                }
              ]
            },
            {
              "name": "app_views_layouts__header_html_erb",
              "type": "class",
              "children": [
                {
                  "name": "render",
                  "type": "function",
                  "labels": [
                    "mvc.template"
                  ],
                  "static": true,
                  "location": "app/views/layouts/_header.html.erb"
                }
              ]
            },
            {
              "name": "app_views_layouts__footer_html_erb",
              "type": "class",
              "children": [
                {
                  "name": "render",
                  "type": "function",
                  "labels": [
                    "mvc.template"
                  ],
                  "static": true,
                  "location": "app/views/layouts/_footer.html.erb"
                }
              ]
            }
          ]
        },
        {
          "name": "helpers",
          "type": "package",
          "children": [
            {
              "name": "ApplicationHelper",
              "type": "class",
              "children": [
                {
                  "name": "full_title",
                  "type": "function",
                  "static": false,
                  "location": "app/helpers/application_helper.rb:4"
                }
              ]
            },
            {
              "name": "SessionsHelper",
              "type": "class",
              "children": [
                {
                  "name": "logged_in?",
                  "type": "function",
                  "static": false,
                  "location": "app/helpers/sessions_helper.rb:40"
                },
                {
                  "name": "current_user",
                  "type": "function",
                  "static": false,
                  "location": "app/helpers/sessions_helper.rb:19"
                }
              ]
            }
          ]
        }
      ]
    },
    {
      "name": "actionview",
      "type": "package",
      "children": [
        {
          "name": "ActionView",
          "type": "class",
          "children": [
            {
              "name": "Resolver",
              "type": "class",
              "children": [
                {
                  "name": "find_all",
                  "type": "function",
                  "labels": [
                    "mvc.template.resolver"
                  ],
                  "static": false,
                  "location": "/usr/local/bundle/gems/actionview-7.0.4/lib/action_view/template/resolver.rb:62"
                }
              ]
            }
          ]
        }
      ]
    },
    {
      "type": "database",
      "name": "Database",
      "children": [
        {
          "type": "query",
          "name": "begin transaction"
        },
        {
          "type": "query",
          "name": "rollback transaction"
        }
      ]
    },
    {
      "type": "http",
      "name": "HTTP server requests",
      "children": [
        {
          "type": "route",
          "name": "GET /contact"
        }
      ]
    }
  ]
}